{"\u767d":{"symbol":"\u767d","relations":[],"story":""},"\u9020":{"symbol":"\u9020","relations":[],"story":"revelation and road to new creation"},"\u9053":{"symbol":"\u9053","relations":[],"story":"stop putting your neck on the roadway!"},"\u9801":{"symbol":"\u9801","relations":[],"story":"looks like a stack of books facing down tied on a branch of leaf.. then a page opened.."},"\u4e09":{"symbol":"\u4e09","relations":[],"story":""},"\u771f":{"symbol":"\u771f","relations":[],"story":"<div><div>Looks like a tool hanging, attached to reality, the true one.<\/div><\/div>"},"\u8feb":{"symbol":"\u8feb","relations":[],"story":"a white road is full with urge and temptation"},"\u7684":{"symbol":"\u7684","relations":[],"story":"white round radle (senduk) that looks like it has a MARK\/bull's eye at the center of it"},"\u9996":{"symbol":"\u9996","relations":[],"story":""},"\u56db":{"symbol":"\u56db","relations":[],"story":""},"\u4e01":{"symbol":"\u4e01","relations":[],"story":""},"\u5bcc":{"symbol":"\u5bcc","relations":[],"story":"a ricefield, a house for a mouth means wealth"},"\u8279":{"symbol":"\u8279","relations":[],"story":""},"\u9003":{"symbol":"\u9003","relations":[],"story":"a road to escape from omen\/portent"},"\u5203":{"symbol":"\u5203","relations":[],"story":"looks like a blade being cut by the edge of a sword"},"\u53e4":{"symbol":"\u53e4","relations":[],"story":""},"\u5144":{"symbol":"\u5144","relations":[],"story":"looks like a leg with mouth, he sure talks a lot like my big brother"},"\u8fba":{"symbol":"\u8fba","relations":[],"story":"a boundary for the road is made with sword"},"\u5b50":{"symbol":"\u5b50","relations":[],"story":""},"\u65e9":{"symbol":"\u65e9","relations":[],"story":""},"\u8096":{"symbol":"\u8096","relations":[],"story":"sparking resemblance of the moon"},"\u66a6":{"symbol":"\u66a6","relations":[],"story":"It takes many years for a cliff to form or erode. A tree takes many months to grow. But days pass by regularly - so in this way, we see the movement of time such as with a CALENDAR."},"\u597d":{"symbol":"\u597d","relations":[],"story":"woman is fond of her child"},"\u65e6":{"symbol":"\u65e6","relations":[],"story":""},"\u7701":{"symbol":"\u7701","relations":[],"story":"few eyes have better focus&nbsp;"},"\u5473":{"symbol":"\u5473","relations":[],"story":"one can only taste a flavor before it is fully entered the mouth"},"\u8eca":{"symbol":"\u8eca","relations":[],"story":"looks like a car if you watch closely"},"\u5916":{"symbol":"\u5916","relations":[],"story":"you dont spend evening near the grave, divining outside"},"\u5343":{"symbol":"\u5343","relations":[],"story":""},"\u7167":{"symbol":"\u7167","relations":[],"story":"a sun, a shining sword, a mouth.. illuminate! it compares!"},"\u9023":{"symbol":"\u9023","relations":[],"story":"when i am on the road i always take along my car, take along me please i wanna follow you on roads"},"\u5999":{"symbol":"\u5999","relations":[],"story":"there're really few exquisite woman in this world"},"\u820c":{"symbol":"\u820c","relations":[],"story":""},"\u6728":{"symbol":"\u6728","relations":[],"story":""},"\u524d":{"symbol":"\u524d","relations":[],"story":"a butcher eyes standing in front of the meat"},"\u5bfa":{"symbol":"\u5bfa","relations":[],"story":"looks like someone sitting under a cross.. is it a temple?<div><br><\/div><div>a buddhist temple?<\/div>"},"\u5902":{"symbol":"\u5902","relations":[],"story":""},"\u5c02":{"symbol":"\u5c02","relations":[],"story":""},"\u690d":{"symbol":"\u690d","relations":[],"story":"from tree to a plant straightaway"},"\u5146":{"symbol":"\u5146","relations":[],"story":"it looks like a view from behind the legs watching a portent momentous event"},"\u83ab":{"symbol":"\u83ab","relations":[],"story":"looks like someone guarding the entry saying you shalt not pass"},"\u5404":{"symbol":"\u5404","relations":[],"story":"each mouth for every legs"},"\u6797":{"symbol":"\u6797","relations":[],"story":""},"\u54e1":{"symbol":"\u54e1","relations":[],"story":""},"\u6848":{"symbol":"\u6848","relations":[],"story":"when women is relaxed in the house surrounded by tree, it's good time to make a plan"},"\u725b":{"symbol":"\u725b","relations":[],"story":"looks like a cow here"},"\u683c":{"symbol":"\u683c","relations":[],"story":"each tree live up to their own status"},"\u6751":{"symbol":"\u6751","relations":[],"story":"many trees glued together becoming a village"},"\u76f8":{"symbol":"\u76f8","relations":[],"story":"many interconnected trees with eyes for each other"},"\u7565":{"symbol":"\u7565","relations":[],"story":"each rice field has it's own abbreviation"},"\u672c":{"symbol":"\u672c","relations":[],"story":"a cut on a tree to make a book"},"\u672a":{"symbol":"\u672a","relations":[],"story":"a tree marked one on top of it is not yet ready to be cut"},"\u4e07":{"symbol":"\u4e07","relations":[],"story":""},"\u8349":{"symbol":"\u8349","relations":[],"story":"many sunflower surrounded by grass... it also looks like a grass field"},"\u5ba2":{"symbol":"\u5ba2","relations":[],"story":"each\/every house can only house a guest"},"\u59b9":{"symbol":"\u59b9","relations":[],"story":"younger sister is not yet a woman"},"\u5177":{"symbol":"\u5177","relations":[],"story":""},"\u8449":{"symbol":"\u8449","relations":[],"story":"a tree flower make a leaf for every generation"},"\u82e5":{"symbol":"\u82e5","relations":[],"story":"the young flower is the right flower"},"\u984d":{"symbol":"\u984d","relations":[],"story":"the guest head has a big forehead"},"\u82e6":{"symbol":"\u82e6","relations":[],"story":"old dying flower living in suffering"},"\u5de5":{"symbol":"\u5de5","relations":[],"story":""},"\u72ac":{"symbol":"\u72ac","relations":[],"story":"a big person often followed by a big dog"},"\u590f":{"symbol":"\u590f","relations":[],"story":"many heads walking in summer"},"\u66ae":{"symbol":"\u66ae","relations":[],"story":"flower, a sun, and a tool make a nice livehood"},"\u82d7":{"symbol":"\u82d7","relations":[],"story":"you need a seedling for the flower field"},"\u53ec":{"symbol":"\u53ec","relations":[],"story":"when a mouth looks like sword it seduce people, it call for people, 'buy from me', 'eat with me', 'drink with me', 'catch cold with me'"},"\u51e6":{"symbol":"\u51e6","relations":[],"story":"a trash is disposed when the wind walks"},"\u9ed9":{"symbol":"\u9ed9","relations":[],"story":"Jack the ripper and his dog makes you SILENCE"},"\u5973":{"symbol":"\u5973","relations":[],"story":""},"\u6d17":{"symbol":"\u6d17","relations":[],"story":"always remember to wash the cow legs with water"},"\u7279":{"symbol":"\u7279","relations":[],"story":"only a special cow get to live in an office"},"\u544a":{"symbol":"\u544a","relations":[],"story":"talking about the revelation of the biblical bull\/cow"},"\u5927":{"symbol":"\u5927","relations":[],"story":""},"\u5408":{"symbol":"\u5408","relations":[],"story":"it really looks like a mouth with a closed eyes trying to take or fit something with"},"\u51e0":{"symbol":"\u51e0","relations":[],"story":""},"\u3078":{"symbol":"\u3078","relations":[],"story":""},"\u843d":{"symbol":"\u843d","relations":[],"story":"each flower fall into the water when the time comes"},"\u5196":{"symbol":"\u5196","relations":[],"story":""},"\u5168":{"symbol":"\u5168","relations":[],"story":"the umbrella can only fit the kings whole body"},"\u68ee":{"symbol":"\u68ee","relations":[],"story":""},"\u8ecd":{"symbol":"\u8ecd","relations":[],"story":"car, crown = tank = army = chariot"},"\u6ce8":{"symbol":"\u6ce8","relations":[],"story":"a king pouring kindness towards his people"},"\u672b":{"symbol":"\u672b","relations":[],"story":"it too long too extreme for a tree top"},"\u535c":{"symbol":"\u535c","relations":[],"story":""},"\u671d":{"symbol":"\u671d","relations":[],"story":"when a mist being next to moon, it has to be a morning really.. somehow during period of a regime an apoch ago"},"\u4e00":{"symbol":"\u4e00","relations":[],"story":""},"\u516b":{"symbol":"\u516b","relations":[],"story":""},"\u6761":{"symbol":"\u6761","relations":[],"story":"a twig sticking out of a tree when it walks"},"\u660e":{"symbol":"\u660e","relations":[],"story":""},"\u5149":{"symbol":"\u5149","relations":[],"story":"this one really looks like an anode\/cathode legs that shoots led ray!"},"\u4e38":{"symbol":"\u4e38","relations":[],"story":""},"\u53e5":{"symbol":"\u53e5","relations":[],"story":"looks like a mouth bound up to say something, a phrase, a sentance"},"\u73fe":{"symbol":"\u73fe","relations":[],"story":"king when he open his eyes, he sees the present"},"\u904b":{"symbol":"\u904b","relations":[],"story":"the road once used to carry an army of cao cao"},"\u5b80":{"symbol":"\u5b80","relations":[],"story":""},"\u7136":{"symbol":"\u7136","relations":[],"story":"i see a dog hugging a moon sort of thing"},"\u4e94":{"symbol":"\u4e94","relations":[],"story":""},"\u5148":{"symbol":"\u5148","relations":[],"story":"there used to be a human with cow legs before"},"\u53e3":{"symbol":"\u53e3","relations":[],"story":""},"\u5922":{"symbol":"\u5922","relations":[],"story":"eye see a vivid evening in a dream full of flowers&nbsp;"},"\u65e5":{"symbol":"\u65e5","relations":[],"story":""},"\u4ecb":{"symbol":"\u4ecb","relations":[],"story":"looks like a road jammed in toward another road"},"\u4e0a":{"symbol":"\u4e0a","relations":[],"story":""},"\u4ea0":{"symbol":"\u4ea0","relations":[],"story":""},"\u65e7":{"symbol":"\u65e7","relations":[],"story":""},"\u754c":{"symbol":"\u754c","relations":[],"story":"this looks like brother of jack the ripper, father of the world"},"\u51e1":{"symbol":"\u51e1","relations":[],"story":"only a mediocre hides from a wind"},"\u9ad8":{"symbol":"\u9ad8","relations":[],"story":"tall building with train coming through under"},"\u5360":{"symbol":"\u5360","relations":[],"story":"those divinition sticking on a table must be doing fortune telling there."},"\u72c2":{"symbol":"\u72c2","relations":[],"story":"looks like a crazy lunatic king"},"\u76f4":{"symbol":"\u76f4","relations":[],"story":"looks like a lamp straightaway hanging on top of a bed, needs to be fix, with honesty"},"\u70b9":{"symbol":"\u70b9","relations":[],"story":"lookings like a lamp\/torch pointing to a spot!"},"\u9811":{"symbol":"\u9811","relations":[],"story":"the beginning of page always start of something stubborn, foolish one"},"\u5448":{"symbol":"\u5448","relations":[],"story":"the king mouth is beautiful display"},"\u4eac":{"symbol":"\u4eac","relations":[],"story":"looks like a person with tophat working in a capital"},"\u4e71":{"symbol":"\u4e71","relations":[],"story":"when a tongue is attached to a hook, it says bad thing that caused riot, war, disorder, disturb"},"\u7406":{"symbol":"\u7406","relations":[],"story":"jack the ri-pper and the king surpass all the logic"},"\u4e86":{"symbol":"\u4e86","relations":[],"story":""},"\u4e36":{"symbol":"\u4e36","relations":[],"story":""},"\u535a":{"symbol":"\u535a","relations":[],"story":"looks like a doctor with phd, someone that's fair in command having a speciality and being exclusive"},"\u6d3b":{"symbol":"\u6d3b","relations":[],"story":"macam tengah menyanyi je tu.. so lively"},"\u571f":{"symbol":"\u571f","relations":[],"story":""},"\u666f":{"symbol":"\u666f","relations":[],"story":"a sun rise over a capital gives a nice scenery"},"\u53ef":{"symbol":"\u53ef","relations":[],"story":"looks like a court with mouth symbol in it, and it gives away meaning of can, or something passable, or do not, should not"},"\u5947":{"symbol":"\u5947","relations":[],"story":"it's a strange giant on top of a station"},"\u898b":{"symbol":"\u898b","relations":[],"story":"this looks like an opened eye, an opened eye can see, has idea, opinion!<br><br>"},"\u5c0f":{"symbol":"\u5c0f","relations":[],"story":"looks like a person holding two small little baby"},"\u5915":{"symbol":"\u5915","relations":[],"story":""},"\u6c34":{"symbol":"\u6c34","relations":[],"story":""},"\u4e8c":{"symbol":"\u4e8c","relations":[],"story":""},"\u540c":{"symbol":"\u540c","relations":[],"story":"looks like a one eyed alien.. all looks the same"},"\u662d":{"symbol":"\u662d","relations":[],"story":"see the sun standing next to something so mischievous, a seduce, a call? it is shining, it's bright!"},"\u539f":{"symbol":"\u539f","relations":[],"story":""},"\u708e":{"symbol":"\u708e","relations":[],"story":"Many fire...<div><br><\/div><div>is inflammation.. flame, blaze!!<\/div>"},"\u4e5d":{"symbol":"\u4e5d","relations":[],"story":""},"\u513f":{"symbol":"\u513f","relations":[],"story":""},"\u820e":{"symbol":"\u820e","relations":[],"story":"imagine a house. this looks like a cottage. see the cross.!"},"\u5468":{"symbol":"\u5468","relations":[],"story":"circumference of a teapot hood"},"\u5b88":{"symbol":"\u5b88","relations":[],"story":""},"\u543e":{"symbol":"\u543e","relations":[],"story":"I feed five mouth"},"\u4e28":{"symbol":"\u4e28","relations":[],"story":""},"\u4e2d":{"symbol":"\u4e2d","relations":[],"story":""},"\u6708":{"symbol":"\u6708","relations":[],"story":""},"\u9031":{"symbol":"\u9031","relations":[],"story":"every week i complete a circomference of roads"},"\u4e0b":{"symbol":"\u4e0b","relations":[],"story":""},"\u5150":{"symbol":"\u5150","relations":[],"story":""},"\u8ca0":{"symbol":"\u8ca0","relations":[],"story":""},"\u58eb":{"symbol":"\u58eb","relations":[],"story":"looks like a person opening arms up like a gentleman"},"\u5207":{"symbol":"\u5207","relations":[],"story":"seven sword cut a sharp one"},"\u5411":{"symbol":"\u5411","relations":[],"story":"looks like a train going beyong the horizon, far yonder, or is it approaching"},"\u91cf":{"symbol":"\u91cf","relations":[],"story":"jack the ri-pper under the sun! he's measuring the quantity\/amount of victims!"},"\u6731":{"symbol":"\u6731","relations":[],"story":""},"\u5bae":{"symbol":"\u5bae","relations":[],"story":"you went to a shrine, a shinto shrine but all you can find is a backbone"},"\u753a":{"symbol":"\u753a","relations":[],"story":"looks like a building or rice field next to a street.. must be town\/village"},"\u5409":{"symbol":"\u5409","relations":[],"story":"kind gentleman say good luck"},"\u52f9":{"symbol":"\u52f9","relations":[],"story":""},"\u77f3":{"symbol":"\u77f3","relations":[],"story":""},"\u58ee":{"symbol":"\u58ee","relations":[],"story":"a ninja turtle wearing a robust weapons"},"\u516d":{"symbol":"\u516d","relations":[],"story":""},"\u58f2":{"symbol":"\u58f2","relations":[],"story":"a gentleman sell legs for a crown"},"\u5143":{"symbol":"\u5143","relations":[],"story":""},"\u52fa":{"symbol":"\u52fa","relations":[],"story":""},"\u5b66":{"symbol":"\u5b66","relations":[],"story":"child study under a schoolhouse"},"\u4e59":{"symbol":"\u4e59","relations":[],"story":"this one also means second as in second party in agreement"},"\u9858":{"symbol":"\u9858","relations":[],"story":"counting for heads for petition in the middle of field\/meadows"},"\u6e90":{"symbol":"\u6e90","relations":[],"story":""},"\u899a":{"symbol":"\u899a","relations":[],"story":"in schoolhouse you open your eyes to memorize"},"\u6709":{"symbol":"\u6709","relations":[],"story":"the moon by one side, is the sign of existence, or something that have occured"},"\u6cca":{"symbol":"\u6cca","relations":[],"story":"white cum overnight"},"\u807f":{"symbol":"\u807f","relations":[],"story":""},"\u5247":{"symbol":"\u5247","relations":[],"story":"just follow the shellfish. it's the rule"},"\u66f8":{"symbol":"\u66f8","relations":[],"story":"with brush you need sunlight to write"},"\u6d25":{"symbol":"\u6d25","relations":[],"story":"drawing an haven with brush and drops of water"},"\u6535":{"symbol":"\u6535","relations":[],"story":"it is a taskmaster"},"\u5225":{"symbol":"\u5225","relations":[],"story":""},"\u5b8c":{"symbol":"\u5b8c","relations":[],"story":"the perfect house is made from beginning, perfection start from the home"},"\u653b":{"symbol":"\u653b","relations":[],"story":"aggression being one of taskmaster craft"},"\u591a":{"symbol":"\u591a","relations":[],"story":"too much evening, too frequent TA, Ta many.."},"\u5382":{"symbol":"\u5382","relations":[],"story":""},"\u6557":{"symbol":"\u6557","relations":[],"story":"a selfish taskmaster led to his failure"},"\u7815":{"symbol":"\u7815","relations":[],"story":""},"\u5182":{"symbol":"\u5182","relations":[],"story":""},"\u7530":{"symbol":"\u7530","relations":[],"story":""},"\u53f3":{"symbol":"\u53f3","relations":[],"story":"mouth by one side speak the right word"},"\u679a":{"symbol":"\u679a","relations":[],"story":"taskmaster giving sheet of the tree he cuts"},"\u5dde":{"symbol":"\u5dde","relations":[],"story":"looks like an highway, many cars trying to enter a state\/province"},"\u81ea":{"symbol":"\u81ea","relations":[],"story":"when an eye is sticking out, it's only looking for oneself"},"\u6545":{"symbol":"\u6545","relations":[],"story":"the task master being too old to be happenstance"},"\u9806":{"symbol":"\u9806","relations":[],"story":"good head follow\/obey the river or order"},"\u6d88":{"symbol":"\u6d88","relations":[],"story":"looks like a broom trying to extinguish the fire"},"\u656c":{"symbol":"\u656c","relations":[],"story":"taskmaster given a flower and phrase for an awe and respect"},"\u572d":{"symbol":"\u572d","relations":[],"story":"too many soils make a square jewel"},"\u8a00":{"symbol":"\u8a00","relations":[],"story":"a mouth with a stacked up words is saying"},"\u6642":{"symbol":"\u6642","relations":[],"story":"a sun rise over the temple is the symbol of time, hour"},"\u592a":{"symbol":"\u592a","relations":[],"story":"big person with plump on his belly"},"\u8b66":{"symbol":"\u8b66","relations":[],"story":"too many says and awe become commandment \/ admonishment"},"\u8a08":{"symbol":"\u8a08","relations":[],"story":"need to say ten things for a plot"},"\u5bc4":{"symbol":"\u5bc4","relations":[],"story":"you're drawing near to this strange house"},"\u706b":{"symbol":"\u706b","relations":[],"story":"YOU CANNOT FORGET THAT THIS IS FIRE! LOOKS LIKE A PERSON HOLDING A FIRE!"},"\u91cc":{"symbol":"\u91cc","relations":[],"story":"it's a jack the ri-pper"},"\u8a70":{"symbol":"\u8a70","relations":[],"story":"good life say a story packed with good lucks"},"\u76ee":{"symbol":"\u76ee","relations":[],"story":""},"\u5b57":{"symbol":"\u5b57","relations":[],"story":"child growing in house makes a character"},"\u54c1":{"symbol":"\u54c1","relations":[],"story":"looks like goods stacked up to be delivered"},"\u5347":{"symbol":"\u5347","relations":[],"story":""},"\u8a71":{"symbol":"\u8a71","relations":[],"story":"a tongue say a good tale of story"},"\u9802":{"symbol":"\u9802","relations":[],"story":""},"\u8a9e":{"symbol":"\u8a9e","relations":[],"story":"you need to say five word to make a sentence"},"\u540d":{"symbol":"\u540d","relations":[],"story":"say my name in the evening"},"\u7802":{"symbol":"\u7802","relations":[],"story":""},"\u8aad":{"symbol":"\u8aad","relations":[],"story":"you need to be able to speak\/say and read to sell thing"},"\u5ddd":{"symbol":"\u5ddd","relations":[],"story":""},"\u767e":{"symbol":"\u767e","relations":[],"story":""},"\u5200":{"symbol":"\u5200","relations":[],"story":"looks like a sword hanging down"},"\u8abf":{"symbol":"\u8abf","relations":[],"story":"with the right circumference to your sayin, you can make the right tune"},"\u57cb":{"symbol":"\u57cb","relations":[],"story":"looks like jack the ri-pper wanna bury you with something"},"\u5b89":{"symbol":"\u5b89","relations":[],"story":"ah, just a women relaxing.. peaceful, quiet, contented, rested.. cheap women.."},"\u8ac7":{"symbol":"\u8ac7","relations":[],"story":"a discussion is where an heated\/inflammation talks happen"},"\u5f0b":{"symbol":"\u5f0b","relations":[],"story":"looks like a bow, with dot indicating a hand pulling an arrow"},"\u4e03":{"symbol":"\u4e03","relations":[],"story":""},"\u5f0f":{"symbol":"\u5f0f","relations":[],"story":"arrow crafted with style"},"\u8a66":{"symbol":"\u8a66","relations":[],"story":"a test is where you style up your the things that you say"},"\u5341":{"symbol":"\u5341","relations":[],"story":""},"\u6bcd":{"symbol":"\u6bcd","relations":[],"story":"looks like a two squared boobs that mama has"},"\u6208":{"symbol":"\u6208","relations":[],"story":"shooting up the arrow as a symbol of celebration and fiesta"},"\u6216":{"symbol":"\u6216","relations":[],"story":"one drunked for some fiesta is enough"},"\u57df":{"symbol":"\u57df","relations":[],"story":"a range of soil can be used for plantation"},"\u620a":{"symbol":"\u620a","relations":[],"story":"a parade does look like a fiesta"},"\u5c11":{"symbol":"\u5c11","relations":[],"story":"looks like a little, so it must be few"},"\u6cc9":{"symbol":"\u6cc9","relations":[],"story":"white water gushing from a spring\/fountain"},"\u7550":{"symbol":"\u7550","relations":[],"story":"one mouth for out ricefield is the sign of wealth"},"\u6210":{"symbol":"\u6210","relations":[],"story":"a fiesta turn into \/ become a parade"},"\u91d1":{"symbol":"\u91d1","relations":[],"story":"the king under the umbrella with all the gold he can keep"},"\u5de6":{"symbol":"\u5de6","relations":[],"story":""},"\u5668":{"symbol":"\u5668","relations":[],"story":"a utensil looks like there are many goods around a tool&nbsp;"},"\u4e16":{"symbol":"\u4e16","relations":[],"story":""},"\u57ce":{"symbol":"\u57ce","relations":[],"story":"it was a castle before it became a soil"},"\u620c":{"symbol":"\u620c","relations":[],"story":"a parade can only do one march"},"\u5a01":{"symbol":"\u5a01","relations":[],"story":"i saw one intimidating woman during a parade"},"\u6ec5":{"symbol":"\u6ec5","relations":[],"story":"one fire destroyed a parade"},"\u6e1b":{"symbol":"\u6e1b","relations":[],"story":"one mouth went hungry and dwindling during a parade"},"\u773a":{"symbol":"\u773a","relations":[],"story":"the eye can only stare at this portent omen"},"\u6c38":{"symbol":"\u6c38","relations":[],"story":"a drop of water for eternity!"},"\u8584":{"symbol":"\u8584","relations":[],"story":"working in flowery office is dilution.. too good to be true"},"\u92ad":{"symbol":"\u92ad","relations":[],"story":"a gold floating coin"},"\u6d45":{"symbol":"\u6d45","relations":[],"story":"a dead body floating in a shallow water"},"\u9b5a":{"symbol":"\u9b5a","relations":[],"story":"looks like a fish trying to run from the cage!"},"\u6b62":{"symbol":"\u6b62","relations":[],"story":""},"\u6b69":{"symbol":"\u6b69","relations":[],"story":"slowing walking by taking a few stops"},"\u6b74":{"symbol":"\u6b74","relations":[],"story":"you can find the curriculum on the school calendar"},"\u6b66":{"symbol":"\u6b66","relations":[],"story":"the warrior stopped when he sees a quiver on the archer back"},"\u6b63":{"symbol":"\u6b63","relations":[],"story":"only one stop needed to make a correction and justice"},"\u8a3c":{"symbol":"\u8a3c","relations":[],"story":"evidence is when you say a correct things"},"\u653f":{"symbol":"\u653f","relations":[],"story":"the good taskmaster stopped caring about politics"},"\u5b9a":{"symbol":"\u5b9a","relations":[],"story":"prior to buying a home, the inspector will come to your house to determine everything that needs mending"},"\u8d70":{"symbol":"\u8d70","relations":[],"story":"you need to run from where the soil is mending"},"\u8d85":{"symbol":"\u8d85","relations":[],"story":"to run from seduction one must trascend"},"\u8d8a":{"symbol":"\u8d8a","relations":[],"story":"you can only surpass your rank when win your run in a parade"},"\u662f":{"symbol":"\u662f","relations":[],"story":"mending the sun just so-so"},"\u984c":{"symbol":"\u984c","relations":[],"story":"everyday a news page will have a just so-so topic"},"\u5ef4":{"symbol":"\u5ef4","relations":[],"story":"the road seems a bit stretched"},"\u5efa":{"symbol":"\u5efa","relations":[],"story":"before you can build something you need to stretch your brush a lot like drawing the plan etc"},"\u8863":{"symbol":"\u8863","relations":[],"story":"I see a big garment here"},"\u88c5":{"symbol":"\u88c5","relations":[],"story":"this attire suit as a garment for the gentleman"},"\u88cf":{"symbol":"\u88cf","relations":[],"story":"this is the back garment of jack the ri-pper"},"\u54c0":{"symbol":"\u54c0","relations":[],"story":"a pathetic person keep buying garments when he only have mouth to feed"},"\u9060":{"symbol":"\u9060","relations":[],"story":"only the road can carry the pathetic teapot at distant"},"\u521d":{"symbol":"\u521d","relations":[],"story":"for the first time a sword is called ne"},"\u5dfe":{"symbol":"\u5dfe","relations":[],"story":"looks like a hanging towel"},"\u5e55":{"symbol":"\u5e55","relations":[],"story":"the curtain is made of towel with pattern of flower, sun on it"},"\u5e03":{"symbol":"\u5e03","relations":[],"story":"the towel is made of linen by one side"},"\u5e02":{"symbol":"\u5e02","relations":[],"story":"M for market of top hats"},"\u59c9":{"symbol":"\u59c9","relations":[],"story":"my elder sister can go to market because she is a woman"},"\u8c9d":{"symbol":"\u8c9d","relations":[],"story":""},"\u5e2f":{"symbol":"\u5e2f","relations":[],"story":"above the apron is the belt or sash"},"\u523a":{"symbol":"\u523a","relations":[],"story":"the tree was wrapped with belt to protect it's thorn"},"\u5236":{"symbol":"\u5236","relations":[],"story":"the cow was tied with belt so it follow the rule and system of law"},"\u4e91":{"symbol":"\u4e91","relations":[],"story":"two lines indicate a quotation mark. a rising cloud that looks like double quote"},"\u8ee2":{"symbol":"\u8ee2","relations":[],"story":"the car had to revolve around when it sees a cloud ahead"},"\u82b8":{"symbol":"\u82b8","relations":[],"story":"only nami has the technique to conjure rising cloud using only flower"},"\u96e8":{"symbol":"\u96e8","relations":[],"story":"no mama.. it is raining"},"\u96f2":{"symbol":"\u96f2","relations":[],"story":"the cloud rises before a rain"},"\u51ab":{"symbol":"\u51ab","relations":[],"story":"2 drop is ice, 3 drop is water"},"\u51ac":{"symbol":"\u51ac","relations":[],"story":"becareful not 2 drop on ice during winter"}}